{
    "name": "Dirty Race",
    "id": 6,

    "environment": {
        "interiorId": 4
    },

    "spawnPositions": [
        {
            "position": [ -1382.5000, -660.0000, 1055.7100 ],
            "facingAngle": 90.0,
            "vehicleModelId": 468
        },
        {
            "position": [ -1382.5000, -663.0000, 1055.7100 ],
            "facingAngle": 90.0,
            "vehicleModelId": 468
        },
        {
            "position": [ -1382.5000, -666.0000, 1055.7100 ],
            "facingAngle": 90.0,
            "vehicleModelId": 468
        },
        {
            "position": [ -1382.5000, -669.0000, 1055.7100 ],
            "facingAngle": 90.0,
            "vehicleModelId": 468
        }
    ],

    "settings": {
        "allowLeaveVehicle": true,
        "unlimitedNos": true
    },

    "checkpoints": [
        { "position": [ -1427.6289, -663.8555, 1059.7811 ], "size": 7.0 },
        { "position": [ -1482.5558, -657.6473, 1055.5725 ], "size": 7.0 },
        { "position": [ -1478.5491, -611.9074, 1055.9659 ], "size": 7.0 },
        { "position": [ -1419.6672, -621.9334, 1052.3190 ], "size": 7.0 },
        { "position": [ -1445.0730, -682.8519, 1053.2527 ], "size": 7.0 },
        { "position": [ -1350.8408, -719.4795, 1055.5349 ], "size": 7.0 },
        { "position": [ -1377.5194, -683.7310, 1053.4545 ], "size": 7.0 },
        { "position": [ -1341.7905, -633.4376, 1053.7496 ], "size": 7.0 },
        { "position": [ -1369.7123, -590.2598, 1055.7078 ], "size": 7.0 },
        { "position": [ -1523.5306, -603.0933, 1055.7491 ], "size": 7.0 },
        { "position": [ -1437.4156, -739.8591, 1053.9781 ], "size": 7.0 },
        { "position": [ -1293.4811, -721.4753, 1052.9530 ], "size": 7.0 }
    ]
}
